setup.py
statsx_distributions/Binomialdistribution.py
statsx_distributions/Gaussiandistribution.py
statsx_distributions/Generaldistribution.py
statsx_distributions/__init__.py
statsx_distributions.egg-info/PKG-INFO
statsx_distributions.egg-info/SOURCES.txt
statsx_distributions.egg-info/dependency_links.txt
statsx_distributions.egg-info/not-zip-safe
statsx_distributions.egg-info/top_level.txt